{"total":26,"pageSize":12,"pageCount":3,"data":[{"title":"python数据分析：xlwings操作excel","uid":"b183580f01b4c460a08090715fbc01f0","slug":"python数据分析：xlwings操作excel","date":"2022-01-16T11:16:09.000Z","updated":"2022-04-03T06:07:37.193Z","comments":true,"path":"api/articles/python数据分析：xlwings操作excel.json","cover":null,"text":"xlwings是Python中操作Excel的一个第三方库，支持.xls读写，.xlsx读写，操作非常简单，功能也很强大xlwings与VBA的配合非常完美，你可以在python中调用VBA，也可以在VBA中使用python编程，这些通过xlwings都可以巧妙实现。先说装这个x...","link":"","photos":[],"count_time":{"symbolsCount":"3.5k","symbolsTime":"3 mins."},"categories":[],"tags":[{"name":"数据分析","slug":"数据分析","count":18,"path":"api/tags/数据分析.json"}],"author":{"name":"Aurora","slug":"blog-author","avatar":"https://img-blog.csdnimg.cn/20210313122054101.png","link":"/","description":"","socials":{"github":"","twitter":"","stackoverflow":"","wechat":"","qq":"","weibo":"","zhihu":"","csdn":"","juejin":"","customs":{}}},"feature":true},{"title":"sql排名函数","uid":"68c9396da13a152d585d7816d6c82312","slug":"sql排名函数","date":"2021-12-23T03:14:23.000Z","updated":"2022-04-03T06:06:41.689Z","comments":true,"path":"api/articles/sql排名函数.json","cover":null,"text":" rank()排名是不连续的，出现同名的排序序号会相同(比较常规的排序)，存在并列，且序号会跳跃 适合求第一名，名次这类 select employee_id ,last_name ,department_id ,salary ,rank() over(partition by ...","link":"","photos":[],"count_time":{"symbolsCount":783,"symbolsTime":"1 mins."},"categories":[],"tags":[{"name":"数据分析","slug":"数据分析","count":18,"path":"api/tags/数据分析.json"}],"author":{"name":"Aurora","slug":"blog-author","avatar":"https://img-blog.csdnimg.cn/20210313122054101.png","link":"/","description":"","socials":{"github":"","twitter":"","stackoverflow":"","wechat":"","qq":"","weibo":"","zhihu":"","csdn":"","juejin":"","customs":{}}},"feature":true},{"title":"sql查询连续签到天数","uid":"1a3e4bd78f5e4ca42de4b5c02b9d4f86","slug":"sql查询连续签到天数","date":"2021-12-20T08:23:46.000Z","updated":"2022-04-03T06:06:49.495Z","comments":true,"path":"api/articles/sql查询连续签到天数.json","cover":null,"text":"先建表 create table user_attendence( user_id bigint comment &#39;用户名&#39;, date TIMESTAMP comment &#39;日期&#39; , is_sign bigint comment &#39;是否...","link":"","photos":[],"count_time":{"symbolsCount":"1.8k","symbolsTime":"2 mins."},"categories":[],"tags":[{"name":"数据分析","slug":"数据分析","count":18,"path":"api/tags/数据分析.json"}],"author":{"name":"Aurora","slug":"blog-author","avatar":"https://img-blog.csdnimg.cn/20210313122054101.png","link":"/","description":"","socials":{"github":"","twitter":"","stackoverflow":"","wechat":"","qq":"","weibo":"","zhihu":"","csdn":"","juejin":"","customs":{}}},"feature":true},{"title":"mysql_tips","uid":"a556aaed3b3be5cc651b39ff50e6148d","slug":"mysql-tips","date":"2021-12-13T08:35:58.000Z","updated":"2022-04-03T06:06:03.198Z","comments":true,"path":"api/articles/mysql-tips.json","cover":null,"text":" 四个在工作后才知道的SQL密技 https://zhuanlan.zhihu.com/p/412878736 mysql基础https://blog.csdn.net/weixin_45108087/article/details/102766281 MYSQL中的COLLAT...","link":"","photos":[],"count_time":{"symbolsCount":"1.6k","symbolsTime":"1 mins."},"categories":[],"tags":[{"name":"数据分析","slug":"数据分析","count":18,"path":"api/tags/数据分析.json"}],"author":{"name":"Aurora","slug":"blog-author","avatar":"https://img-blog.csdnimg.cn/20210313122054101.png","link":"/","description":"","socials":{"github":"","twitter":"","stackoverflow":"","wechat":"","qq":"","weibo":"","zhihu":"","csdn":"","juejin":"","customs":{}}}},{"title":"python办公自动化：操作excel","uid":"7df2c9f61f81e14813ba612502b886c1","slug":"python办公自动化：操作excel","date":"2021-12-08T14:28:43.000Z","updated":"2022-04-03T06:09:41.283Z","comments":true,"path":"api/articles/python办公自动化：操作excel.json","cover":null,"text":"#python 使用 openpyxl 操作 excel openpyxl 最好用的 python 操作 excel 表格库，不接受反驳（想反驳自己去学其他的） openpyxl 官网链接：https://openpyxl.readthedocs.io/en/stable/ ht...","link":"","photos":[],"count_time":{"symbolsCount":"10k","symbolsTime":"9 mins."},"categories":[],"tags":[{"name":"自动化","slug":"自动化","count":4,"path":"api/tags/自动化.json"}],"author":{"name":"Aurora","slug":"blog-author","avatar":"https://img-blog.csdnimg.cn/20210313122054101.png","link":"/","description":"","socials":{"github":"","twitter":"","stackoverflow":"","wechat":"","qq":"","weibo":"","zhihu":"","csdn":"","juejin":"","customs":{}}}},{"title":"python中requests使用中文乱码的解决方案","uid":"8a288770ed82450aa993ccbeacfd0367","slug":"requests乱码问题解决","date":"2021-12-02T15:30:02.000Z","updated":"2022-04-03T06:07:01.852Z","comments":true,"path":"api/articles/requests乱码问题解决.json","cover":null,"text":" 中文乱码处理import requests url &#x3D; &quot;http:&#x2F;&#x2F;www.baidu.com&quot; r &#x3D; requests.get(url) # 自动选择合适的编码方式 r.encoding &#x3D; r.ap...","link":"","photos":[],"count_time":{"symbolsCount":"1.7k","symbolsTime":"2 mins."},"categories":[],"tags":[{"name":"数据分析","slug":"数据分析","count":18,"path":"api/tags/数据分析.json"}],"author":{"name":"Aurora","slug":"blog-author","avatar":"https://img-blog.csdnimg.cn/20210313122054101.png","link":"/","description":"","socials":{"github":"","twitter":"","stackoverflow":"","wechat":"","qq":"","weibo":"","zhihu":"","csdn":"","juejin":"","customs":{}}}},{"title":"Python数据分析 :pandas数据读取、预处理、筛选、计算，时间序列、透视、拼接、导出","uid":"74df2b30e38d008e4f87b397961dd215","slug":"Python数据分析：pandas数据读取、预处理、筛选、计算，时间序列、透视、拼接、导出","date":"2021-10-04T06:02:22.000Z","updated":"2022-04-03T06:07:50.214Z","comments":true,"path":"api/articles/Python数据分析：pandas数据读取、预处理、筛选、计算，时间序列、透视、拼接、导出.json","cover":null,"text":"一、Pandas数据结构S1&#x3D;pd.Series([‘a’,’b’,’c’]) series是一组数据与一组索引（行索引）组成的数据结构 S1&#x3D;pd.Series([‘a’,’b’,’c’],index&#x3D;(1,3,4)) 指定索引 S1&#x3D;p...","link":"","photos":[],"count_time":{"symbolsCount":"22k","symbolsTime":"20 mins."},"categories":[],"tags":[{"name":"数据分析","slug":"数据分析","count":18,"path":"api/tags/数据分析.json"}],"author":{"name":"Aurora","slug":"blog-author","avatar":"https://img-blog.csdnimg.cn/20210313122054101.png","link":"/","description":"","socials":{"github":"","twitter":"","stackoverflow":"","wechat":"","qq":"","weibo":"","zhihu":"","csdn":"","juejin":"","customs":{}}}},{"title":"python办公自动化：pdf和word","uid":"3cd7e57c6f854790d628f23694417fc5","slug":"python办公自动化：pdf和word","date":"2021-08-26T06:16:31.000Z","updated":"2022-04-03T06:10:22.109Z","comments":true,"path":"api/articles/python办公自动化：pdf和word.json","cover":null,"text":"python 使用 PyPDF2 和 pdfplumber 操作pdf PyPDF2 官网：https://pythonhosted.org/PyPDF2/ PyPDF2 可以更好的读取、写入、分割、合并 PDF 文件； pdfplumber 官网：https://github....","link":"","photos":[],"count_time":{"symbolsCount":"7.5k","symbolsTime":"7 mins."},"categories":[],"tags":[{"name":"自动化","slug":"自动化","count":4,"path":"api/tags/自动化.json"}],"author":{"name":"Aurora","slug":"blog-author","avatar":"https://img-blog.csdnimg.cn/20210313122054101.png","link":"/","description":"","socials":{"github":"","twitter":"","stackoverflow":"","wechat":"","qq":"","weibo":"","zhihu":"","csdn":"","juejin":"","customs":{}}}},{"title":"sql数据分析：自动化报表，多场景持续更新","uid":"ce3f6facdcd7d14d49266cce6ca90c5e","slug":"sql数据分析：自动化报表，多场景更新","date":"2021-08-06T15:19:59.000Z","updated":"2022-04-03T06:06:35.307Z","comments":true,"path":"api/articles/sql数据分析：自动化报表，多场景更新.json","cover":null,"text":"建表CREATE TABLE &#96;cd_20210414&#96; ( &#96;id&#96; int(11) NOT NULL AUTO_INCREMENT, &#96;platform&#96; varchar(10) CHARACTER SET utf8mb4 CO...","link":"","photos":[],"count_time":{"symbolsCount":"17k","symbolsTime":"16 mins."},"categories":[],"tags":[{"name":"数据分析","slug":"数据分析","count":18,"path":"api/tags/数据分析.json"}],"author":{"name":"Aurora","slug":"blog-author","avatar":"https://img-blog.csdnimg.cn/20210313122054101.png","link":"/","description":"","socials":{"github":"","twitter":"","stackoverflow":"","wechat":"","qq":"","weibo":"","zhihu":"","csdn":"","juejin":"","customs":{}}}},{"title":"python-flask疫情数据可视化","uid":"d36edaa00a28ef96e171ed217c165e70","slug":"python-flask疫情数据可视化","date":"2021-07-21T06:18:39.000Z","updated":"2022-04-03T06:06:25.002Z","comments":true,"path":"api/articles/python-flask疫情数据可视化.json","cover":null,"text":"Flask是一个轻量级的web框架，看了https://www.bilibili.com/video/BV177411j7qJ 大佬的视频，做的一个疫情可视化项目,（电脑屏幕小看着有点拥挤。大屏展示还是挺好看的），热搜词云的数据找不到网站了，就弄了个表格；自己修改了一些部分，感兴...","link":"","photos":[],"count_time":{"symbolsCount":309,"symbolsTime":"1 mins."},"categories":[],"tags":[{"name":"数据分析","slug":"数据分析","count":18,"path":"api/tags/数据分析.json"}],"author":{"name":"Aurora","slug":"blog-author","avatar":"https://img-blog.csdnimg.cn/20210313122054101.png","link":"/","description":"","socials":{"github":"","twitter":"","stackoverflow":"","wechat":"","qq":"","weibo":"","zhihu":"","csdn":"","juejin":"","customs":{}}}},{"title":"python连接mysql:读取、写入、更新、删除","uid":"f671959f062d49d2d4345cd4aa269a83","slug":"python数据分析：连接mysql，读取、写入、更新、删除","date":"2021-07-04T05:16:15.000Z","updated":"2022-04-03T06:07:42.361Z","comments":true,"path":"api/articles/python数据分析：连接mysql，读取、写入、更新、删除.json","cover":null,"text":"1、连接读取数据第一种：用pymysql连接#安装pymysql conda install pymysql #或者 pip install pymysql import pymysql #创建数据库连接，依次是主机名，用户名，密码，要打开的数据库，端口号和编码类型 def ge...","link":"","photos":[],"count_time":{"symbolsCount":"6.6k","symbolsTime":"6 mins."},"categories":[],"tags":[{"name":"数据分析","slug":"数据分析","count":18,"path":"api/tags/数据分析.json"}],"author":{"name":"Aurora","slug":"blog-author","avatar":"https://img-blog.csdnimg.cn/20210313122054101.png","link":"/","description":"","socials":{"github":"","twitter":"","stackoverflow":"","wechat":"","qq":"","weibo":"","zhihu":"","csdn":"","juejin":"","customs":{}}}},{"title":"python数据可视化：pyecharts v1版本","uid":"c5a3632aecdc3f50f32639748c6ea233","slug":"python数据可视化：pyecharts-v1版本","date":"2021-06-05T02:29:26.000Z","updated":"2022-04-03T06:06:56.542Z","comments":true,"path":"api/articles/python数据可视化：pyecharts-v1版本.json","cover":null,"text":"Echarts是一个由百度开源的数据可视化，结合巧妙的交互性，精巧的图表设计；而 Python 是一门富有表达力的语言，很适合用于数据处理。分析遇上数据可视化时，pyecharts诞生了。个人觉得可视化最好用的，不接受反驳，毕竟用echarts的都那么多；官方文档 自己挑了一些碰...","link":"","photos":[],"count_time":{"symbolsCount":"17k","symbolsTime":"16 mins."},"categories":[],"tags":[{"name":"数据分析","slug":"数据分析","count":18,"path":"api/tags/数据分析.json"}],"author":{"name":"Aurora","slug":"blog-author","avatar":"https://img-blog.csdnimg.cn/20210313122054101.png","link":"/","description":"","socials":{"github":"","twitter":"","stackoverflow":"","wechat":"","qq":"","weibo":"","zhihu":"","csdn":"","juejin":"","customs":{}}}}]}